mcclient/__init__.py
mcclient/address.py
mcclient/base_client.py
mcclient/bedrock_client.py
mcclient/query_client.py
mcclient/response.py
mcclient/slp.py
mcclient/packet/__init__.py
mcclient/packet/inbound.py
mcclient/packet/outbound.py
mcclient/packet/varint.py
mcclient_lib-1.2.0.dist-info/LICENSE
mcclient_lib-1.2.0.dist-info/METADATA
mcclient_lib-1.2.0.dist-info/WHEEL
mcclient_lib-1.2.0.dist-info/top_level.txt
mcclient_lib-1.2.0.dist-info/RECORD
