Metadata-Version: 2.1
Name: mcclient-lib
Version: 1.2.0
Summary: A lightweight Minecraft client for querying the status data of a Minecraft server.
Author-email: Sch8ill <noreply@noreply.com>
Project-URL: Bug Tracker, https://github.com/sch8ill/mcclient-lib/issues
Project-URL: Homepage, https://github.com/Sch8ill/mcclient-lib
Classifier: Programming Language :: Python :: 3
Classifier: License :: OSI Approved :: MIT License
Classifier: Operating System :: OS Independent
Requires-Python: >=3.7
License-File: LICENSE
Requires-Dist: dnspython >=2.2.1
